hanzo_tools/__init__.py
hanzo_tools/todo/__init__.py
hanzo_tools/todo/base.py
hanzo_tools/todo/todo_tool.py
hanzo_tools_todo-0.2.0.dist-info/METADATA
hanzo_tools_todo-0.2.0.dist-info/WHEEL
hanzo_tools_todo-0.2.0.dist-info/entry_points.txt
hanzo_tools_todo-0.2.0.dist-info/top_level.txt
hanzo_tools_todo-0.2.0.dist-info/RECORD
