Metadata-Version: 2.4
Name: hanzo-tools-todo
Version: 0.2.0
Summary: Task management tools for Hanzo MCP
Author-email: Hanzo Industries Inc <dev@hanzo.ai>
License: MIT
Keywords: hanzo,tools,todo,task,mcp,ai
Requires-Python: >=3.12
Requires-Dist: hanzo-tools-core>=0.1.0
Requires-Dist: mcp>=1.25.0
Requires-Dist: pydantic>=2.12.5
